{
  "schemaVersion": 1,
  "id": "craftingstation",
  "version": "${version}",

  "name": "Crafting Station",
  "description": "Adds a Crafting Station",
  "authors": [
    "AshIndigo"
  ],
  "contact": {
    "homepage": "https://fabricmc.net/",
    "sources": "https://github.com/AshIndigo/CraftingStation"
  },

  "license": "CC0-1.0",
  "icon": "assets/craftingstation/icon.png",

  "environment": "*",
  "entrypoints": {
    "main": [
      "com.ashindigo.craftingstation.CraftingStation"
    ],
    "client": [
      "com.ashindigo.craftingstation.CraftingStationClient"
    ]
  },
  "mixins": [
  ],

  "depends": {
    "fabricloader": ">=0.4.0",
    "fabric": "*",
    "spinnery": ">=2.0.17+fabric-20w06a"
  },
  "suggests": {
  }
}
